nvim_remote/__init__.py
nvim_remote/nvr.py
nvim_remote-4.2.0.dist-info/LICENSE
nvim_remote-4.2.0.dist-info/METADATA
nvim_remote-4.2.0.dist-info/WHEEL
nvim_remote-4.2.0.dist-info/entry_points.txt
nvim_remote-4.2.0.dist-info/RECORD
