Metadata-Version: 2.1
Name: nvim-remote
Version: 4.2.0
Summary: Control nvim processes using "nvr" commandline tool
Home-page: https://github.com/1995parham/nvim-remote
License: MIT
Keywords: nvim-remote,neovim-remote,nvr
Author: Parham Alvani
Author-email: parham.alvani@gmail.com
Requires-Python: >=3.12
Classifier: License :: OSI Approved :: MIT License
Classifier: Programming Language :: Python :: 3
Classifier: Programming Language :: Python :: 3.12
Classifier: Programming Language :: Python :: 3.13
Requires-Dist: psutil (>=5.9.6,<7.0.0)
Requires-Dist: pynvim (>=0.5.0,<0.6.0)
Project-URL: Repository, https://github.com/1995parham/nvim-remote
